vcoin/__init__.py
vcoin/admin.py
vcoin/apps.py
vcoin/models.py
vcoin/views.py
vcoin-0.1.1.5.dist-info/LICENSE
vcoin-0.1.1.5.dist-info/METADATA
vcoin-0.1.1.5.dist-info/WHEEL
vcoin-0.1.1.5.dist-info/top_level.txt
vcoin-0.1.1.5.dist-info/RECORD
