Metadata-Version: 2.1
Name: vcoin
Version: 0.1.1.5
Summary: 虚拟币专用模块.
Home-page: https://hehuoya.com
Author: lichanghong
Author-email: 1211054926@qq.com
License: BSD License
Platform: UNKNOWN
Classifier: License :: OSI Approved :: MIT License
Classifier: Intended Audience :: Developers
Classifier: Operating System :: OS Independent
Classifier: Programming Language :: Python
Classifier: Programming Language :: Python :: 3
Classifier: Programming Language :: Python :: 3.3
Classifier: Programming Language :: Python :: 3.4
Classifier: Programming Language :: Python :: 3.5
License-File: LICENSE
Requires-Dist: Crypto
Requires-Dist: hhycommon
